{
  "Happy New Year Wishes": {
    "Wishes in 100 languages": "https://www.happy-new-year.org/wishes/new-year-wishes-in-100-langauges.html",
    "Wishes in Indian Languages": "https://www.happy-new-year.org/wishes/",
    "Wishes in European Languages": "https://www.happy-new-year.org/wishes/",
    "Popular Languages": "https://www.happy-new-year.org/wishes/10-popular-languages.html",
    "Cards": "https://www.happy-new-year.org/cards/",
    "Easter Festival": "https://www.happy-new-year.org/festivals/easter/",
    "26-bihari-wishes": "https://www.happy-new-year.org/2026/26-bihari-wishes.html",
    "26-chinese-new-year-wishes": "https://www.happy-new-year.org/2026/26-chinese-new-year-wishes.html",
    "26-christmas-wishes": "https://www.happy-new-year.org/2026/26-christmas-wishes.html",
    "2026-festival-countdown": "https://www.happy-new-year.org/2026/2026-festival-countdown.html",
    "Christmas-wishes-by-audience": "https://www.happy-new-year.org/2026/christmas-wishes-by-audience.html",
    "Happy-new-year-2026-celebrations-worldwide.html": "https://www.happy-new-year.org/2026/happy-new-year-2026-celebrations-worldwide.html.html",
    "Happy-new-year-2026": "https://www.happy-new-year.org/2026/happy-new-year-2026.html",
    "Multilingual-greetings-webpage": "https://www.happy-new-year.org/2026/multilingual-greetings-webpage.html"
  },
  "International New Year": {
    "Chinese New Year": "https://www.happy-new-year.org/chinese-new-year/",
    "Lunar and Solar Hindu Year": "https://www.happy-new-year.org/hindu-new-year/",
    "Jewesh Roash Hashanah": "https://www.happy-new-year.org/jewish-new-year/",
    "Islamic New Year": "https://www.happy-new-year.org/islamic-new-year/",
    "Japanese New Year": "https://www.happy-new-year.org/japanese-new-year/",
    "Hindu Festival Calendar 2026": "https://www.happy-new-year.org/2026/hindu-festivals-2026.html",
    "Pitu Paksha 2026": "https://www.happy-new-year.org/2026/pitru-paksha-2026.html"
  },
  "Folders": {},
  "Pages": {
    "Delicious Dussehra Recipes Traditional Festive Foods": "https://www.happy-new-year.org/festivals/dusshera/delicious-dussehra-recipes-traditional-festive-foods.html",
    "Diy Dussehra Decorations Creative Ideas": "https://www.happy-new-year.org/festivals/dusshera/diy-dussehra-decorations-creative-ideas.html",
    "Dussehra Celebrations Across India Regional Traditions": "https://www.happy-new-year.org/festivals/dusshera/dussehra-celebrations-across-india-regional-traditions.html",
    "Dussehra Crafts For Kids Fun Educational Projects": "https://www.happy-new-year.org/festivals/dusshera/dussehra-crafts-for-kids-fun-educational-projects.html",
    "Dussehra Festivals Around The World Global Celebrations": "https://www.happy-new-year.org/festivals/dusshera/dussehra-festivals-around-the-world-global-celebrations.html",
    "Dussehra In Modern Times Adapting Traditions": "https://www.happy-new-year.org/festivals/dusshera/dussehra-in-modern-times-adapting-traditions.html",
    "Dussehra Quotes Wishes Sharing Spirit Festival": "https://www.happy-new-year.org/festivals/dusshera/dussehra-quotes-wishes-sharing-spirit-festival.html",
    "Eco Friendly Dussehra Sustainable Ways To Celebrate": "https://www.happy-new-year.org/festivals/dusshera/eco-friendly-dussehra-sustainable-ways-to-celebrate.html",
    "History Significance Of Dussehra Triumph Good Over Evil": "https://www.happy-new-year.org/festivals/dusshera/history-significance-of-dussehra-triumph-good-over-evil.html",
    "Importance Of Navratri Leading To Dussehra": "https://www.happy-new-year.org/festivals/dusshera/importance-of-navratri-leading-to-dussehra.html",
    "Planning Dussehra Celebration Tips Memorable Event": "https://www.happy-new-year.org/festivals/dusshera/planning-dussehra-celebration-tips-memorable-event.html",
    "Prepare For Dussehra Rituals Shopping Festivities": "https://www.happy-new-year.org/festivals/dusshera/prepare-for-dussehra-rituals-shopping-festivities.html",
    "Significance Of Ramlila Performances During Dussehra": "https://www.happy-new-year.org/festivals/dusshera/significance-of-ramlila-performances-during-dussehra.html",
    "Story Of Lord Rama And Ravana Essence Of Dussehra": "https://www.happy-new-year.org/festivals/dusshera/story-of-lord-rama-and-ravana-essence-of-dussehra.html",
    "Symbolism Of Effigy Burning On Dussehra": "https://www.happy-new-year.org/festivals/dusshera/symbolism-of-effigy-burning-on-dussehra.html"
  },
  "Footer Links": {
    "Privacy Policy": "https://www.happy-new-year.org/privacypolicy,html",
    "Sitemap": "https://www.happy-new-year.org/sitemap.html"
  }
}