{
  "Happy New Year Wishes": {
    "Wishes in 100 languages": "https://www.happy-new-year.org/wishes/new-year-wishes-in-100-langauges.html",
    "Wishes in Indian Languages": "https://www.happy-new-year.org/wishes/",
    "Wishes in European Languages": "https://www.happy-new-year.org/wishes/",
    "Popular Languages": "https://www.happy-new-year.org/wishes/10-popular-languages.html",
    "Cards": "https://www.happy-new-year.org/cards/",
    "Easter Festival": "https://www.happy-new-year.org/festivals/easter/",
    "26-bihari-wishes": "https://www.happy-new-year.org/2026/26-bihari-wishes.html",
    "26-chinese-new-year-wishes": "https://www.happy-new-year.org/2026/26-chinese-new-year-wishes.html",
    "26-christmas-wishes": "https://www.happy-new-year.org/2026/26-christmas-wishes.html",
    "2026-festival-countdown": "https://www.happy-new-year.org/2026/2026-festival-countdown.html",
    "Christmas-wishes-by-audience": "https://www.happy-new-year.org/2026/christmas-wishes-by-audience.html",
    "Happy-new-year-2026-celebrations-worldwide.html": "https://www.happy-new-year.org/2026/happy-new-year-2026-celebrations-worldwide.html.html",
    "Happy-new-year-2026": "https://www.happy-new-year.org/2026/happy-new-year-2026.html",
    "Multilingual-greetings-webpage": "https://www.happy-new-year.org/2026/multilingual-greetings-webpage.html"
  },
  "International New Year": {
    "Chinese New Year": "https://www.happy-new-year.org/chinese-new-year/",
    "Lunar and Solar Hindu Year": "https://www.happy-new-year.org/hindu-new-year/",
    "Jewesh Roash Hashanah": "https://www.happy-new-year.org/jewish-new-year/",
    "Islamic New Year": "https://www.happy-new-year.org/islamic-new-year/",
    "Japanese New Year": "https://www.happy-new-year.org/japanese-new-year/",
    "Hindu Festival Calendar 2026": "https://www.happy-new-year.org/2026/hindu-festivals-2026.html",
    "Pitu Paksha 2026": "https://www.happy-new-year.org/2026/pitru-paksha-2026.html"
  },
  "Folders": {
    "100 Languages": "https://www.happy-new-year.org/wishes/100-languages/",
    "In Languages": "https://www.happy-new-year.org/wishes/in-languages/"
  },
  "Pages": {
    "10 Popular Languages": "https://www.happy-new-year.org/wishes/10-popular-languages.html",
    "Christmas Wishes By Audience": "https://www.happy-new-year.org/wishes/christmas-wishes-by-audience.html",
    "Facebook": "https://www.happy-new-year.org/wishes/facebook.html",
    "Grand Children": "https://www.happy-new-year.org/wishes/grand-children.html",
    "Grand Parents": "https://www.happy-new-year.org/wishes/grand-parents.html",
    "Happy New Year 2026 Wishes In 100 Langauges": "https://www.happy-new-year.org/wishes/happy-new-year-2026-wishes-in-100-langauges.html",
    "Happy New Year 2026 Multilingual Greetings Webpage": "https://www.happy-new-year.org/wishes/happy_new_year_2026_multilingual_greetings_webpage.html",
    "Happy New Year 2026 Multilingual Greetings Webpage With Voice": "https://www.happy-new-year.org/wishes/happy_new_year_2026_multilingual_greetings_webpage_with_voice.html",
    "Linkedin": "https://www.happy-new-year.org/wishes/linkedin.html",
    "New Year And Wishes Around The World": "https://www.happy-new-year.org/wishes/new-year-and-wishes-around-the-world.html",
    "New Year Wishes In 100 Langauges": "https://www.happy-new-year.org/wishes/new-year-wishes-in-100-langauges.html",
    "Newyear History Celebration": "https://www.happy-new-year.org/wishes/newyear-history-celebration.html",
    "Newyear History": "https://www.happy-new-year.org/wishes/newyear-history.html",
    "Newyear Info": "https://www.happy-new-year.org/wishes/newyear-info.html",
    "Parents": "https://www.happy-new-year.org/wishes/parents.html",
    "Quotes": "https://www.happy-new-year.org/wishes/quotes.html",
    "Son": "https://www.happy-new-year.org/wishes/son.html",
    "Wishes Kids": "https://www.happy-new-year.org/wishes/wishes-kids.html",
    "Wishes Parents": "https://www.happy-new-year.org/wishes/wishes-parents.html",
    "Wishes Professional": "https://www.happy-new-year.org/wishes/wishes-professional.html",
    "Wishes Relatives": "https://www.happy-new-year.org/wishes/wishes-relatives.html",
    "Wishes Spouse": "https://www.happy-new-year.org/wishes/wishes-spouse.html"
  },
  "Footer Links": {
    "Privacy Policy": "https://www.happy-new-year.org/privacypolicy,html",
    "Sitemap": "https://www.happy-new-year.org/sitemap.html"
  }
}