[
  {
    "id": "2008-movies",
    "title": "Top 10 Must-Watch Movies with High IMDb Ratings",
    "url": "https://www.happy-new-year.org/2008/2008-movies.html",
    "category": "2008",
    "description": "The article is a table listing the movie title, director, genre, and IMDb rating of ten popular movies including The Dark Knight, Slumdog Millionaire, and Iron Man.",
    "keywords": [
      "Movie titles",
      "Directors",
      "Genres",
      "IMDb ratings",
      "The Dark Knight",
      "Slumdog Millionaire",
      "WALL-E",
      "The Curious Case of Benjamin Button",
      "Frost/Nixon",
      "Milk",
      "The Wrestler",
      "Gran Torino",
      "Iron Man",
      "Revolutionary Road."
    ]
  },
  {
    "id": "2008-news",
    "title": "Top Headlines of 2008: From Oil Prices to Presidential Elections",
    "url": "https://www.happy-new-year.org/2008/2008-news.html",
    "category": "2008",
    "description": "The article is a table listing major events that occurred in 2008, including the collapse of investment banks, record high oil prices, the Beijing Olympics, and the election of Barack Obama as President of the United States.",
    "keywords": [
      "Dates",
      "Headlines",
      "Oil prices",
      "Super Tuesday",
      "Bear Stearns",
      "Barack Obama",
      "Earthquake in China",
      "Summer Olympics",
      "Lehman Brothers",
      "Bailout package."
    ]
  },
  {
    "id": "2008-oscar-awards",
    "title": "Oscar Winners 2009: Slumdog, Sean Penn, and Heath Ledger Shine",
    "url": "https://www.happy-new-year.org/2008/2008-oscar-awards.html",
    "category": "2008",
    "description": "The article lists the winners of the major categories at the 2009 Academy Awards, including Best Picture for Slumdog Millionaire and posthumous Best Supporting Actor for Heath Ledger in The Dark Knight.",
    "keywords": [
      "Awards",
      "Winners",
      "Films",
      "Directors",
      "Actors",
      "Actresses",
      "Screenplays",
      "Animated Feature",
      "Foreign Language Film",
      "Descriptions."
    ]
  },
  {
    "id": "index",
    "title": "Top news for year 2008 | new movies awards",
    "url": "https://www.happy-new-year.org/2008/index.html",
    "category": "2008",
    "description": "Top news for year 2008 | new movies awards Top news for year 2008 | new movies awards Home Date Headline January 1, 2008 Oil prices reach record high of $100...",
    "keywords": [
      "index",
      "year",
      "nbsp",
      "drama",
      "known",
      "slumdog",
      "millionaire",
      "his"
    ]
  }
]