[
  {
    "id": "Diwali-aarti-photo",
    "title": "Diwali-aarti-photo",
    "url": "https://www.happy-new-year.org/wallpapers/Diwali/Diwali-aarti-photo.html",
    "category": "Diwali",
    "description": "Diwali-aarti-photo Diwali-aarti-photo Home Diwali-aarti-photo Home &nbsp;&nbsp;&nbsp;&nbsp; Diwali-aarti-photo &nbsp;&nbsp;&nbsp;&nbsp; Diwali-decoration-d...",
    "keywords": [
      "diwali",
      "aarti",
      "photo",
      "nbsp",
      "year",
      "diwali-aarti-photo",
      "hindu",
      "different"
    ]
  },
  {
    "id": "Diwali-decoration-diya-symbol",
    "title": "Diwali-decoration-diya-symbol",
    "url": "https://www.happy-new-year.org/wallpapers/Diwali/Diwali-decoration-diya-symbol.html",
    "category": "Diwali",
    "description": "Diwali-decoration-diya-symbol Diwali-decoration-diya-symbol Home Diwali-decoration-diya-symbol Home &nbsp;&nbsp;&nbsp;&nbsp; Diwali-aarti-photo...",
    "keywords": [
      "diwali",
      "decoration",
      "diya",
      "symbol",
      "nbsp",
      "year",
      "diwali-decoration-diya-symbol",
      "hindu"
    ]
  },
  {
    "id": "Diwali-puja-image",
    "title": "Diwali-puja-image",
    "url": "https://www.happy-new-year.org/wallpapers/Diwali/Diwali-puja-image.html",
    "category": "Diwali",
    "description": "Diwali-puja-image Diwali-puja-image Home Diwali-puja-image Home &nbsp;&nbsp;&nbsp;&nbsp; Diwali-aarti-photo &nbsp;&nbsp;&nbsp;&nbsp; Diwali-decoration-d...",
    "keywords": [
      "diwali",
      "puja",
      "image",
      "nbsp",
      "year",
      "diwali-puja-image",
      "hindu",
      "diwali-aarti-photo"
    ]
  },
  {
    "id": "happy-diwali-decorations-diyas",
    "title": "happy-diwali-decorations-diyas",
    "url": "https://www.happy-new-year.org/wallpapers/Diwali/happy-diwali-decorations-diyas.html",
    "category": "Diwali",
    "description": "happy-diwali-decorations-diyas happy-diwali-decorations-diyas Home happy-diwali-decorations-diyas Home &nbsp;&nbsp;&nbsp;&nbsp; Diwali-aarti-photo...",
    "keywords": [
      "happy",
      "diwali",
      "decorations",
      "diyas",
      "nbsp",
      "year",
      "happy-diwali-decorations-diyas",
      "hindu"
    ]
  },
  {
    "id": "happy-diwali-symbols",
    "title": "happy-diwali-symbols",
    "url": "https://www.happy-new-year.org/wallpapers/Diwali/happy-diwali-symbols.html",
    "category": "Diwali",
    "description": "happy-diwali-symbols happy-diwali-symbols Home happy-diwali-symbols Home &nbsp;&nbsp;&nbsp;&nbsp; Diwali-aarti-photo &nbsp;&nbsp;&nbsp;&nbsp;...",
    "keywords": [
      "happy",
      "diwali",
      "symbols",
      "nbsp",
      "year",
      "happy-diwali-symbols",
      "hindu",
      "diwali-aarti-photo"
    ]
  },
  {
    "id": "index",
    "title": "Diwali festival wallpapers",
    "url": "https://www.happy-new-year.org/wallpapers/Diwali/index.html",
    "category": "Diwali",
    "description": "Diwali festival wallpapers Diwali festival wallpapers Home Diwali festival wallpapers DIWALI AARTI PHOTO &nbsp;&nbsp;&nbsp;&nbsp;&nbsp;&nbsp;&nbsp;&nbsp;...",
    "keywords": [
      "index",
      "nbsp",
      "year",
      "diwali",
      "wallpapers",
      "hindu",
      "happy",
      "islamic"
    ]
  }
]