{
  "Happy New Year Wishes": {
    "Wishes in 100 languages": "https://www.happy-new-year.org/wishes/new-year-wishes-in-100-langauges.html",
    "Wishes in Indian Languages": "https://www.happy-new-year.org/wishes/",
    "Wishes in European Languages": "https://www.happy-new-year.org/wishes/",
    "Popular Languages": "https://www.happy-new-year.org/wishes/10-popular-languages.html",
    "Cards": "https://www.happy-new-year.org/cards/",
    "Easter Festival": "https://www.happy-new-year.org/festivals/easter/",
    "26-bihari-wishes": "https://www.happy-new-year.org/2026/26-bihari-wishes.html",
    "26-chinese-new-year-wishes": "https://www.happy-new-year.org/2026/26-chinese-new-year-wishes.html",
    "26-christmas-wishes": "https://www.happy-new-year.org/2026/26-christmas-wishes.html",
    "2026-festival-countdown": "https://www.happy-new-year.org/2026/2026-festival-countdown.html",
    "Christmas-wishes-by-audience": "https://www.happy-new-year.org/2026/christmas-wishes-by-audience.html",
    "Happy-new-year-2026-celebrations-worldwide.html": "https://www.happy-new-year.org/2026/happy-new-year-2026-celebrations-worldwide.html.html",
    "Happy-new-year-2026": "https://www.happy-new-year.org/2026/happy-new-year-2026.html",
    "Multilingual-greetings-webpage": "https://www.happy-new-year.org/2026/multilingual-greetings-webpage.html"
  },
  "International New Year": {
    "Chinese New Year": "https://www.happy-new-year.org/chinese-new-year/",
    "Lunar and Solar Hindu Year": "https://www.happy-new-year.org/hindu-new-year/",
    "Jewesh Roash Hashanah": "https://www.happy-new-year.org/jewish-new-year/",
    "Islamic New Year": "https://www.happy-new-year.org/islamic-new-year/",
    "Japanese New Year": "https://www.happy-new-year.org/japanese-new-year/",
    "Hindu Festival Calendar 2026": "https://www.happy-new-year.org/2026/hindu-festivals-2026.html",
    "Pitu Paksha 2026": "https://www.happy-new-year.org/2026/pitru-paksha-2026.html"
  },
  "Folders": {
    "Apr": "https://www.happy-new-year.org/2016/Apr/",
    "Aug": "https://www.happy-new-year.org/2016/Aug/",
    "Dec": "https://www.happy-new-year.org/2016/Dec/",
    "Feb": "https://www.happy-new-year.org/2016/Feb/",
    "Jan": "https://www.happy-new-year.org/2016/Jan/",
    "Jul": "https://www.happy-new-year.org/2016/Jul/",
    "Jun": "https://www.happy-new-year.org/2016/Jun/",
    "Mar": "https://www.happy-new-year.org/2016/Mar/",
    "May": "https://www.happy-new-year.org/2016/May/",
    "Nov": "https://www.happy-new-year.org/2016/Nov/",
    "Oct": "https://www.happy-new-year.org/2016/Oct/",
    "Olympics": "https://www.happy-new-year.org/2016/olympics/",
    "Sep": "https://www.happy-new-year.org/2016/Sep/"
  },
  "Pages": {
    "2016 Movies": "https://www.happy-new-year.org/2016/2016-movies.html",
    "2016 News": "https://www.happy-new-year.org/2016/2016-news.html",
    "2016 Oscar Awards": "https://www.happy-new-year.org/2016/2016-oscar-awards.html",
    "2017 News": "https://www.happy-new-year.org/2016/2017-news.html",
    "51 Real Estate News": "https://www.happy-new-year.org/2016/51-real-estate-news.html",
    "51 Stock News": "https://www.happy-new-year.org/2016/51-stock-news.html",
    "51 Tax News": "https://www.happy-new-year.org/2016/51-tax-news.html",
    "Grammy": "https://www.happy-new-year.org/2016/grammy.html",
    "Movies": "https://www.happy-new-year.org/2016/movies.html",
    "Noble Prizes": "https://www.happy-new-year.org/2016/noble-prizes.html",
    "Oscar": "https://www.happy-new-year.org/2016/Oscar.html",
    "Special Places To Visit In 2016": "https://www.happy-new-year.org/2016/Special places to visit in 2016.html",
    "Top 50 Universities Of Usa": "https://www.happy-new-year.org/2016/top-50-universities-of-usa.html",
    "Top Cars": "https://www.happy-new-year.org/2016/top-cars.html",
    "Top Gadgets": "https://www.happy-new-year.org/2016/top-gadgets.html",
    "Top Hindi Movies": "https://www.happy-new-year.org/2016/top-hindi-movies.html",
    "Top Movies": "https://www.happy-new-year.org/2016/top-movies.html",
    "Top News": "https://www.happy-new-year.org/2016/top-news.html"
  },
  "Footer Links": {
    "Privacy Policy": "https://www.happy-new-year.org/privacypolicy,html",
    "Sitemap": "https://www.happy-new-year.org/sitemap.html"
  }
}